time_array/__init__.py
myst_connectors-0.0.1.dist-info/LICENSE
myst_connectors-0.0.1.dist-info/METADATA
myst_connectors-0.0.1.dist-info/WHEEL
myst_connectors-0.0.1.dist-info/top_level.txt
myst_connectors-0.0.1.dist-info/RECORD
